mikeplus/__init__.py
mikeplus/conflicts.py
mikeplus/database.py
mikeplus/dotnet.py
mikeplus/queries.py
mikeplus/shortcuts.py
mikeplus/simulation_runner.py
mikeplus/utils.py
mikeplus/bin/DHI.Mike.Install.dll
mikeplus/bin/runtimeconfig.json
mikeplus/scenarios/__init__.py
mikeplus/scenarios/alternative.py
mikeplus/scenarios/alternative_group.py
mikeplus/scenarios/alternative_group_collection.py
mikeplus/scenarios/scenario.py
mikeplus/scenarios/scenario_collection.py
mikeplus/tables/__init__.py
mikeplus/tables/base_geometry_table.py
mikeplus/tables/base_node_table.py
mikeplus/tables/base_table.py
mikeplus/tables/base_table_collection.py
mikeplus/tables/base_table_columns.py
mikeplus/tables/auto_generated/__init__.py
mikeplus/tables/auto_generated/m21_pfsKeyword.py
mikeplus/tables/auto_generated/m21_pfsParam.py
mikeplus/tables/auto_generated/m21_pfsSection.py
mikeplus/tables/auto_generated/m2d_ADDecay.py
mikeplus/tables/auto_generated/m2d_ADDispersion.py
mikeplus/tables/auto_generated/m2d_ADDispersionArea.py
mikeplus/tables/auto_generated/m2d_ADDispersionD.py
mikeplus/tables/auto_generated/m2d_ADEvaporation.py
mikeplus/tables/auto_generated/m2d_ADEvaporationArea.py
mikeplus/tables/auto_generated/m2d_ADEvaporationD.py
mikeplus/tables/auto_generated/m2d_ADInfiltration.py
mikeplus/tables/auto_generated/m2d_ADInfiltrationArea.py
mikeplus/tables/auto_generated/m2d_ADInfiltrationD.py
mikeplus/tables/auto_generated/m2d_ADInitalCondition.py
mikeplus/tables/auto_generated/m2d_ADInitalConditionArea.py
mikeplus/tables/auto_generated/m2d_ADInitalConditionD.py
mikeplus/tables/auto_generated/m2d_ADPrecipitation.py
mikeplus/tables/auto_generated/m2d_ADPrecipitationArea.py
mikeplus/tables/auto_generated/m2d_ADPrecipitationD.py
mikeplus/tables/auto_generated/m2d_BndDistributedSource.py
mikeplus/tables/auto_generated/m2d_BndQHRelation.py
mikeplus/tables/auto_generated/m2d_Boundary.py
mikeplus/tables/auto_generated/m2d_Coupling.py
mikeplus/tables/auto_generated/m2d_CouplingConn.py
mikeplus-2026.0.0.dist-info/METADATA
mikeplus-2026.0.0.dist-info/WHEEL
mikeplus-2026.0.0.dist-info/licenses/LICENSE
mikeplus-2026.0.0.dist-info/RECORD
