Metadata-Version: 2.4
Name: mikeplus
Version: 2026.0.0
Summary: A python script package to manipulate MIKE+ database, run simulation by using MIKE+ data, run tools based on MIKE+ data
Project-URL: Homepage, https://github.com/DHI/mikepluspy
Project-URL: Bug Tracker, https://github.com/DHI/mikepluspy/issues
Author-email: Ryan Walter Murray <rywm@dhigroup.com>, Wen Wu <WUW@dhigroup.com>
License-File: LICENSE
Classifier: Development Status :: 2 - Pre-Alpha
Classifier: Intended Audience :: Science/Research
Classifier: License :: OSI Approved :: Apache Software License
Classifier: Programming Language :: Python
Classifier: Programming Language :: Python :: 3
Classifier: Programming Language :: Python :: 3.10
Classifier: Programming Language :: Python :: 3.11
Classifier: Programming Language :: Python :: 3.12
Classifier: Programming Language :: Python :: 3.13
Classifier: Topic :: Scientific/Engineering
Requires-Python: >=3.10
Requires-Dist: numpy
Requires-Dist: pandas
Requires-Dist: pythonnet>=3.0
Provides-Extra: dev
Requires-Dist: ipykernel>=6.29.5; extra == 'dev'
Requires-Dist: jinja2>=3.0.0; extra == 'dev'
Requires-Dist: mypy==1.15.0; extra == 'dev'
Requires-Dist: pandas-stubs>=2.2.2.240807; extra == 'dev'
Requires-Dist: pytest; extra == 'dev'
Requires-Dist: ruff; extra == 'dev'
Requires-Dist: shapely; extra == 'dev'
Provides-Extra: docs
Requires-Dist: quartodoc==0.10.0; extra == 'docs'
Provides-Extra: test
Requires-Dist: jinja2>=3.0.0; extra == 'test'
Requires-Dist: mypy==1.15.0; extra == 'test'
Requires-Dist: pandas-stubs>=2.2.2.240807; extra == 'test'
Requires-Dist: pytest; extra == 'test'
Requires-Dist: pytest-timeout; extra == 'test'
Requires-Dist: shapely; extra == 'test'
